setup.py
tbww.py
TBWW.egg-info/PKG-INFO
TBWW.egg-info/SOURCES.txt
TBWW.egg-info/dependency_links.txt
TBWW.egg-info/requires.txt
TBWW.egg-info/top_level.txt