Metadata-Version: 1.0
Name: TBWW
Version: 0.2.10
Summary: Telegram Bot Wrapper Wraper
Home-page: UNKNOWN
Author: UNKNOWN
Author-email: UNKNOWN
License: GNU GPL 3.0
Platform: UNKNOWN
